dx/__init__.py
dx/config.py
dx/dx.py
dx/formatters/__init__.py
dx/formatters/callouts.py
dx/formatters/dataresource.py
dx/formatters/dx.py
dx/formatters/main.py
dx/formatters/utils.py
dx/settings.py
dx/tests/__init__.py
dx/tests/conftest.py
dx/tests/test_dataresource.py
dx/tests/test_dx.py
dx/tests/test_extras.py
dx/tests/test_registering.py
dx/types.py
dx-1.1.0.dist-info/LICENSE
dx-1.1.0.dist-info/WHEEL
dx-1.1.0.dist-info/METADATA
dx-1.1.0.dist-info/RECORD
