Metadata-Version: 2.1
Name: dx
Version: 1.1.0
Summary: Python wrapper for Data Explorer
Home-page: https://app.noteable.io/
License: BSD
Keywords: data,exploration,visualization
Author: Dave Shoup
Author-email: dave.shoup@gmail.com
Requires-Python: >=3.8,<4.0
Classifier: License :: Other/Proprietary License
Classifier: Programming Language :: Python :: 3
Classifier: Programming Language :: Python :: 3.10
Classifier: Programming Language :: Python :: 3.8
Classifier: Programming Language :: Python :: 3.9
Requires-Dist: ipython (>=7.31.1)
Requires-Dist: pandas (>=1.3.5,<2.0.0)
Requires-Dist: pydantic (>=1.9.1,<2.0.0)
Project-URL: Repository, https://github.com/noteable-io/dx
